{"cameraMode":{"drawMode":0,"name":"Shaded","section":"Shading Mode"},"sceneLighting":true,"audioPlay":false,"sceneViewState":{"showFog":true,"showMaterialUpdate":false,"showSkybox":true,"showFlares":true,"showImageEffects":true,"showParticleSystems":true},"in2DMode":false,"pivot":{"x":-43.404052734375,"y":31.69135284423828,"z":-71.79135131835938},"rotation":{"x":0.06384065002202988,"y":0.9200029373168945,"z":-0.16883860528469087,"w":0.34786808490753176},"size":83.28482055664063,"orthographic":false}